smlr/__init__.py
smlr/cli.py
smlr/dct.py
smlr/smlr.py
smlr-0.1.1.dist-info/licenses/LICENSE
smlr-0.1.1.dist-info/METADATA
smlr-0.1.1.dist-info/WHEEL
smlr-0.1.1.dist-info/entry_points.txt
smlr-0.1.1.dist-info/top_level.txt
smlr-0.1.1.dist-info/RECORD
