Metadata-Version: 2.4
Name: smlr
Version: 0.1.1
Summary: A simple image compression tool
Home-page: https://github.com/yourusername/smlr
Author: Jack Douglas
License: MIT
Project-URL: Repository, https://github.com/J-Douglas/smlr
Project-URL: Issues, https://github.com/J-Douglas/smlr/issues
Requires-Python: >=3.7
License-File: LICENSE
Requires-Dist: numpy
Requires-Dist: scipy
Requires-Dist: matplotlib
Requires-Dist: Pillow
Requires-Dist: importlib_metadata; python_version < "3.8"
Dynamic: home-page
Dynamic: license-file
Dynamic: requires-python
